d_project/__init__.py
d_project/app.py
d_project/schema.py
d_project/utils.py
d_project-0.1.2.dist-info/LICENSE
d_project-0.1.2.dist-info/METADATA
d_project-0.1.2.dist-info/WHEEL
d_project-0.1.2.dist-info/entry_points.txt
d_project-0.1.2.dist-info/RECORD
