Metadata-Version: 2.1
Name: d-project
Version: 0.1.2
Summary: 项目流程管理命令行工具
Author: wangmengdi
Author-email: wangmengdi@smart-insight.com.cn
Requires-Python: >=3.7,<4.0
Classifier: Programming Language :: Python :: 3
Classifier: Programming Language :: Python :: 3.7
Classifier: Programming Language :: Python :: 3.8
Classifier: Programming Language :: Python :: 3.9
Classifier: Programming Language :: Python :: 3.10
Classifier: Programming Language :: Python :: 3.11
Requires-Dist: confection (>=0.1.3,<0.2.0)
Requires-Dist: rich (>=13.3.1)
Requires-Dist: typer (>=0.7.0)
Requires-Dist: wasabi (>=1.1.1)
